_decidalo_client_version.py
decidalo_client/__init__.py
decidalo_client/client.py
decidalo_client/exceptions.py
decidalo_client/py.typed
decidalo_client/models/__init__.py
decidalo_client/models/_autogenerated.py
decidalo_client-0.0.2.dist-info/METADATA
decidalo_client-0.0.2.dist-info/WHEEL
decidalo_client-0.0.2.dist-info/licenses/LICENSE
decidalo_client-0.0.2.dist-info/RECORD
