Metadata-Version: 2.4
Name: decidalo_client
Version: 0.0.2
Summary: An async Python client for the decidalo V3 Import API
Project-URL: Changelog, https://github.com/Hochfrequenz/decidalo_client.py/releases
Project-URL: Homepage, https://github.com/Hochfrequenz/decidalo_client.py
Author-email: Hochfrequenz Unternehmensberatung GmbH <info@hochfrequenz.de>
License: MIT
License-File: LICENSE
Keywords: aiohttp,api,async,client,decidalo,pydantic
Classifier: Development Status :: 4 - Beta
Classifier: Environment :: Console
Classifier: Intended Audience :: Developers
Classifier: License :: OSI Approved :: MIT License
Classifier: Operating System :: OS Independent
Classifier: Programming Language :: Python
Classifier: Programming Language :: Python :: 3 :: Only
Classifier: Programming Language :: Python :: 3.11
Classifier: Programming Language :: Python :: 3.12
Classifier: Programming Language :: Python :: 3.13
Classifier: Programming Language :: Python :: 3.14
Requires-Python: >=3.11
Requires-Dist: aiohttp>=3.10
Requires-Dist: pydantic>=2.5
Provides-Extra: codegen
Requires-Dist: datamodel-code-generator==0.53.0; extra == 'codegen'
Provides-Extra: coverage
Requires-Dist: coverage==7.13.1; extra == 'coverage'
Provides-Extra: dev
Requires-Dist: pip-tools; extra == 'dev'
Provides-Extra: formatting
Requires-Dist: black==25.12.0; extra == 'formatting'
Requires-Dist: isort==7.0.0; extra == 'formatting'
Provides-Extra: linting
Requires-Dist: pylint==4.0.4; extra == 'linting'
Provides-Extra: packaging
Requires-Dist: build==1.4.0; extra == 'packaging'
Requires-Dist: twine==6.2.0; extra == 'packaging'
Provides-Extra: spell-check
Requires-Dist: codespell==2.4.1; extra == 'spell-check'
Provides-Extra: tests
Requires-Dist: aioresponses==0.7.8; extra == 'tests'
Requires-Dist: pytest-asyncio==0.25.0; extra == 'tests'
Requires-Dist: pytest==8.3.5; extra == 'tests'
Provides-Extra: type-check
Requires-Dist: mypy==1.19.1; extra == 'type-check'
Requires-Dist: mypy[pydantic]; extra == 'type-check'
